wechaty_puppet_hostie/__init__.py
wechaty_puppet_hostie/config.py
wechaty_puppet_hostie/puppet.py
wechaty_puppet_hostie-0.4.1.dist-info/LICENSE
wechaty_puppet_hostie-0.4.1.dist-info/METADATA
wechaty_puppet_hostie-0.4.1.dist-info/WHEEL
wechaty_puppet_hostie-0.4.1.dist-info/top_level.txt
wechaty_puppet_hostie-0.4.1.dist-info/RECORD
