Metadata-Version: 2.1
Name: wechaty-puppet-hostie
Version: 0.4.1
Summary: Python Hostie Puppet for Wechaty
Home-page: https://github.com/wechaty/python-wechaty-puppet-hostie
Author: Huan LI (李卓桓)
Author-email: zixia@zixia.net
License: Apache-2.0
Platform: UNKNOWN
Classifier: Programming Language :: Python :: 3.7
Classifier: License :: OSI Approved :: Apache Software License
Classifier: Operating System :: OS Independent
Requires-Dist: grpclib
Requires-Dist: pyee
Requires-Dist: requests
Requires-Dist: chatie-grpc
Requires-Dist: wechaty-puppet
